{
    "contracts_list": [
      {
        "name": "contract0",
        "start": 89,
        "duration": 1,
        "price": 12
      },
      {
        "name": "contract1",
        "start": 87,
        "duration": 77,
        "price": 52
      },
      {
        "name": "contract2",
        "start": 40,
        "duration": 82,
        "price": 67
      },
      {
        "name": "contract3",
        "start": 19,
        "duration": 11,
        "price": 40
      },
      {
        "name": "contract4",
        "start": 50,
        "duration": 86,
        "price": 70
      },
      {
        "name": "contract5",
        "start": 87,
        "duration": 43,
        "price": 63
      },
      {
        "name": "contract6",
        "start": 29,
        "duration": 26,
        "price": 68
      },
      {
        "name": "contract7",
        "start": 58,
        "duration": 45,
        "price": 58
      },
      {
        "name": "contract8",
        "start": 19,
        "duration": 17,
        "price": 42
      },
      {
        "name": "contract9",
        "start": 16,
        "duration": 94,
        "price": 37
      },
      {
        "name": "contract10",
        "start": 70,
        "duration": 74,
        "price": 23
      },
      {
        "name": "contract11",
        "start": 1,
        "duration": 55,
        "price": 26
      },
      {
        "name": "contract12",
        "start": 88,
        "duration": 77,
        "price": 23
      },
      {
        "name": "contract13",
        "start": 68,
        "duration": 81,
        "price": 51
      },
      {
        "name": "contract14",
        "start": 85,
        "duration": 6,
        "price": 23
      },
      {
        "name": "contract15",
        "start": 22,
        "duration": 26,
        "price": 33
      },
      {
        "name": "contract16",
        "start": 37,
        "duration": 88,
        "price": 22
      },
      {
        "name": "contract17",
        "start": 37,
        "duration": 54,
        "price": 20
      },
      {
        "name": "contract18",
        "start": 44,
        "duration": 63,
        "price": 47
      },
      {
        "name": "contract19",
        "start": 62,
        "duration": 57,
        "price": 42
      },
      {
        "name": "contract20",
        "start": 88,
        "duration": 27,
        "price": 62
      },
      {
        "name": "contract21",
        "start": 55,
        "duration": 38,
        "price": 70
      },
      {
        "name": "contract22",
        "start": 62,
        "duration": 70,
        "price": 65
      },
      {
        "name": "contract23",
        "start": 15,
        "duration": 42,
        "price": 48
      },
      {
        "name": "contract24",
        "start": 15,
        "duration": 66,
        "price": 40
      },
      {
        "name": "contract25",
        "start": 60,
        "duration": 18,
        "price": 41
      },
      {
        "name": "contract26",
        "start": 98,
        "duration": 7,
        "price": 52
      },
      {
        "name": "contract27",
        "start": 4,
        "duration": 25,
        "price": 74
      },
      {
        "name": "contract28",
        "start": 17,
        "duration": 12,
        "price": 12
      },
      {
        "name": "contract29",
        "start": 53,
        "duration": 86,
        "price": 73
      },
      {
        "name": "contract30",
        "start": 17,
        "duration": 13,
        "price": 4
      },
      {
        "name": "contract31",
        "start": 64,
        "duration": 24,
        "price": 54
      },
      {
        "name": "contract32",
        "start": 50,
        "duration": 84,
        "price": 92
      },
      {
        "name": "contract33",
        "start": 87,
        "duration": 78,
        "price": 37
      },
      {
        "name": "contract34",
        "start": 77,
        "duration": 76,
        "price": 5
      },
      {
        "name": "contract35",
        "start": 96,
        "duration": 36,
        "price": 80
      },
      {
        "name": "contract36",
        "start": 64,
        "duration": 61,
        "price": 89
      },
      {
        "name": "contract37",
        "start": 91,
        "duration": 22,
        "price": 73
      },
      {
        "name": "contract38",
        "start": 83,
        "duration": 68,
        "price": 76
      },
      {
        "name": "contract39",
        "start": 31,
        "duration": 48,
        "price": 4
      },
      {
        "name": "contract40",
        "start": 65,
        "duration": 17,
        "price": 70
      },
      {
        "name": "contract41",
        "start": 29,
        "duration": 30,
        "price": 74
      },
      {
        "name": "contract42",
        "start": 95,
        "duration": 54,
        "price": 45
      },
      {
        "name": "contract43",
        "start": 55,
        "duration": 47,
        "price": 8
      },
      {
        "name": "contract44",
        "start": 23,
        "duration": 94,
        "price": 34
      },
      {
        "name": "contract45",
        "start": 68,
        "duration": 58,
        "price": 8
      },
      {
        "name": "contract46",
        "start": 43,
        "duration": 53,
        "price": 10
      },
      {
        "name": "contract47",
        "start": 73,
        "duration": 4,
        "price": 10
      },
      {
        "name": "contract48",
        "start": 3,
        "duration": 62,
        "price": 26
      },
      {
        "name": "contract49",
        "start": 45,
        "duration": 96,
        "price": 28
      },
      {
        "name": "contract50",
        "start": 80,
        "duration": 17,
        "price": 63
      },
      {
        "name": "contract51",
        "start": 66,
        "duration": 1,
        "price": 74
      },
      {
        "name": "contract52",
        "start": 95,
        "duration": 44,
        "price": 66
      },
      {
        "name": "contract53",
        "start": 17,
        "duration": 41,
        "price": 36
      },
      {
        "name": "contract54",
        "start": 38,
        "duration": 20,
        "price": 98
      },
      {
        "name": "contract55",
        "start": 38,
        "duration": 59,
        "price": 26
      },
      {
        "name": "contract56",
        "start": 99,
        "duration": 61,
        "price": 25
      },
      {
        "name": "contract57",
        "start": 24,
        "duration": 67,
        "price": 23
      },
      {
        "name": "contract58",
        "start": 95,
        "duration": 40,
        "price": 97
      },
      {
        "name": "contract59",
        "start": 7,
        "duration": 41,
        "price": 18
      },
      {
        "name": "contract60",
        "start": 0,
        "duration": 80,
        "price": 22
      },
      {
        "name": "contract61",
        "start": 37,
        "duration": 1,
        "price": 81
      },
      {
        "name": "contract62",
        "start": 50,
        "duration": 58,
        "price": 77
      },
      {
        "name": "contract63",
        "start": 54,
        "duration": 94,
        "price": 20
      },
      {
        "name": "contract64",
        "start": 54,
        "duration": 6,
        "price": 27
      },
      {
        "name": "contract65",
        "start": 88,
        "duration": 64,
        "price": 40
      },
      {
        "name": "contract66",
        "start": 90,
        "duration": 19,
        "price": 57
      },
      {
        "name": "contract67",
        "start": 78,
        "duration": 9,
        "price": 45
      },
      {
        "name": "contract68",
        "start": 32,
        "duration": 36,
        "price": 21
      },
      {
        "name": "contract69",
        "start": 6,
        "duration": 30,
        "price": 45
      },
      {
        "name": "contract70",
        "start": 95,
        "duration": 1,
        "price": 97
      },
      {
        "name": "contract71",
        "start": 83,
        "duration": 58,
        "price": 11
      },
      {
        "name": "contract72",
        "start": 37,
        "duration": 10,
        "price": 8
      },
      {
        "name": "contract73",
        "start": 11,
        "duration": 73,
        "price": 22
      },
      {
        "name": "contract74",
        "start": 92,
        "duration": 30,
        "price": 29
      },
      {
        "name": "contract75",
        "start": 57,
        "duration": 5,
        "price": 69
      },
      {
        "name": "contract76",
        "start": 50,
        "duration": 40,
        "price": 14
      },
      {
        "name": "contract77",
        "start": 46,
        "duration": 95,
        "price": 63
      },
      {
        "name": "contract78",
        "start": 15,
        "duration": 51,
        "price": 9
      },
      {
        "name": "contract79",
        "start": 39,
        "duration": 68,
        "price": 56
      },
      {
        "name": "contract80",
        "start": 23,
        "duration": 85,
        "price": 77
      },
      {
        "name": "contract81",
        "start": 98,
        "duration": 21,
        "price": 16
      },
      {
        "name": "contract82",
        "start": 90,
        "duration": 78,
        "price": 52
      },
      {
        "name": "contract83",
        "start": 16,
        "duration": 4,
        "price": 66
      },
      {
        "name": "contract84",
        "start": 19,
        "duration": 11,
        "price": 41
      },
      {
        "name": "contract85",
        "start": 77,
        "duration": 56,
        "price": 89
      },
      {
        "name": "contract86",
        "start": 63,
        "duration": 89,
        "price": 19
      },
      {
        "name": "contract87",
        "start": 47,
        "duration": 88,
        "price": 58
      },
      {
        "name": "contract88",
        "start": 19,
        "duration": 1,
        "price": 67
      },
      {
        "name": "contract89",
        "start": 60,
        "duration": 40,
        "price": 67
      },
      {
        "name": "contract90",
        "start": 27,
        "duration": 71,
        "price": 37
      },
      {
        "name": "contract91",
        "start": 36,
        "duration": 62,
        "price": 4
      },
      {
        "name": "contract92",
        "start": 9,
        "duration": 6,
        "price": 36
      },
      {
        "name": "contract93",
        "start": 70,
        "duration": 51,
        "price": 39
      },
      {
        "name": "contract94",
        "start": 41,
        "duration": 93,
        "price": 83
      },
      {
        "name": "contract95",
        "start": 44,
        "duration": 7,
        "price": 75
      },
      {
        "name": "contract96",
        "start": 34,
        "duration": 98,
        "price": 78
      },
      {
        "name": "contract97",
        "start": 86,
        "duration": 65,
        "price": 74
      },
      {
        "name": "contract98",
        "start": 84,
        "duration": 14,
        "price": 14
      },
      {
        "name": "contract99",
        "start": 37,
        "duration": 10,
        "price": 63
      }
    ]
  }